lqreports/__init__.py
lqreports/constants.py
lqreports/resource.py
lqreports/segments.py
lqreports/util.py
lqreports/resources/aframe.min.js
lqreports/resources/liquer.png
lqreports/resources/materialdesignicons.min.css
lqreports/resources/plotly.min.js
lqreports/resources/resources.json
lqreports/resources/resources.yaml
lqreports/resources/vue-resource.js
lqreports/resources/vue-router.js
lqreports/resources/vue.js
lqreports/resources/vuetify.js
lqreports/resources/vuetify.min.css
liquer_reports-0.0.5.dist-info/LICENSE
liquer_reports-0.0.5.dist-info/METADATA
liquer_reports-0.0.5.dist-info/WHEEL
liquer_reports-0.0.5.dist-info/top_level.txt
liquer_reports-0.0.5.dist-info/RECORD
